build/lib/referee/__init__.py
build/lib/referee/cli.py
build/lib/referee/doc2vec.py
build/lib/referee/download.py
build/lib/referee/input.py
build/lib/referee/progress.py
build/lib/referee/settings.py
build/lib/referee/suggest.py
build/lib/referee/utils.py
build/lib/referee/database/__init__.py
build/lib/referee/database/biorxiv.py
build/lib/referee/database/database.py
build/lib/referee/database/semantic_scholar.py
build/lib/tests/__init__.py
build/lib/tests/make_test_database.py
build/lib/tests/test_suggest.py
referee/__init__.py
referee/cli.py
referee/doc2vec.py
referee/download.py
referee/input.py
referee/progress.py
referee/settings.py
referee/suggest.py
referee/utils.py
referee/database/__init__.py
referee/database/biorxiv.py
referee/database/database.py
referee/database/semantic_scholar.py
tests/__init__.py
tests/make_test_database.py
tests/test_suggest.py
principledinvestigator-0.dist-info/LICENSE
principledinvestigator-0.dist-info/METADATA
principledinvestigator-0.dist-info/WHEEL
principledinvestigator-0.dist-info/entry_points.txt
principledinvestigator-0.dist-info/top_level.txt
principledinvestigator-0.dist-info/RECORD
