Metadata-Version: 2.1
Name: principledinvestigator
Version: 0
Summary: not yet
Home-page: https://github.com/FedeClaudi/principledinvestigator
Author: Federico Claudi
License: UNKNOWN
Platform: UNKNOWN
Classifier: Development Status :: 3 - Alpha
Classifier: Operating System :: POSIX :: Linux
Classifier: Operating System :: Microsoft :: Windows :: Windows 10
Classifier: Operating System :: MacOS :: MacOS X
Classifier: Programming Language :: Python
Classifier: Programming Language :: Python :: 3.6
Classifier: Programming Language :: Python :: 3.7
Classifier: Programming Language :: Python :: 3.8
Classifier: Intended Audience :: Developers
Classifier: Intended Audience :: Science/Research
Requires-Python: <3.9
Requires-Dist: pyinspect
Requires-Dist: gensim
Requires-Dist: nltk
Requires-Dist: langdetect
Requires-Dist: pandas
Requires-Dist: loguru
Requires-Dist: requests
Requires-Dist: myterial
Requires-Dist: rich
Requires-Dist: bibtexparser
Requires-Dist: cython
Requires-Dist: typer
